pydown/__init__.py
pydown/cli.py
pydown/engines.py
pydown/handlers.py
pydown/manager.py
pydown/models.py
pydown/observers.py
pydown/utils.py
py_downx-1.1.0.dist-info/LICENSE
py_downx-1.1.0.dist-info/METADATA
py_downx-1.1.0.dist-info/WHEEL
py_downx-1.1.0.dist-info/entry_points.txt
py_downx-1.1.0.dist-info/top_level.txt
py_downx-1.1.0.dist-info/RECORD
