Metadata-Version: 2.1
Name: py-downx
Version: 1.1.0
Summary: Flexible download manager
Home-page: https://github.com/still-standing88/pydown/
Author: still-standing88
License: MIT
Keywords: pydown py-down download downloads
Classifier: Development Status :: 4 - Beta
Classifier: License :: OSI Approved :: MIT License
Classifier: Programming Language :: Python :: 3
Classifier: Programming Language :: Python :: 3.6
Classifier: Programming Language :: Python :: 3.7
Classifier: Programming Language :: Python :: 3.8
Classifier: Programming Language :: Python :: 3.9
Classifier: Programming Language :: Python :: 3.10
Classifier: Topic :: Software Development :: Documentation
Classifier: Topic :: Utilities
Requires-Python: >=3.8
License-File: LICENSE
Requires-Dist: humanize
Requires-Dist: validators
Requires-Dist: paramiko
Requires-Dist: httpx
Requires-Dist: dataclasses-json
